antydan/__init__.py
antydan/main.py
antydan/types.py
tests/__init__.py
tests/conftest.py
tests/test_main.py
tests/test_version.py
antydan-0.0.0a0.dist-info/LICENSE
antydan-0.0.0a0.dist-info/METADATA
antydan-0.0.0a0.dist-info/WHEEL
antydan-0.0.0a0.dist-info/top_level.txt
antydan-0.0.0a0.dist-info/RECORD
